mixprops/__init__.py
mixprops/cli.py
mixprops/constants.py
mixprops/data/species_T_1000_6000.csv
mixprops/data/species_T_200_1000.csv
mixprops/database.py
mixprops/mixture.py
mixprops/settings.py
mixprops/species.py
mixprops/state.py
mixprops/units.py
mixprops-0.4.0.dist-info/LICENSE
mixprops-0.4.0.dist-info/METADATA
mixprops-0.4.0.dist-info/WHEEL
mixprops-0.4.0.dist-info/entry_points.txt
mixprops-0.4.0.dist-info/RECORD
