Metadata-Version: 2.1
Name: mixprops
Version: 0.4.0
Summary: Mixture properties calculator
License: MIT
Author: Oliver Aarnikoivu
Author-email: oliveraarnikoivu@icloud.com
Requires-Python: >=3.8.1
Classifier: License :: OSI Approved :: MIT License
Classifier: Programming Language :: Python :: 3
Classifier: Programming Language :: Python :: 3.9
Classifier: Programming Language :: Python :: 3.10
Classifier: Programming Language :: Python :: 3.11
Requires-Dist: pandas (>=2.0.3,<3.0.0)
Requires-Dist: pydantic (>=2.0.2,<3.0.0)
Requires-Dist: pydantic-settings (>=2.0.1,<3.0.0)
Requires-Dist: pyyaml (>=6.0,<7.0)
